AdresseParser/AdresseParser.py
AdresseParser/__init__.py
AdresseParser/cedex.py
AdresseParser/codes_postaux.py
AdresseParser/departements.py
AdresseParser-1.0.9.dist-info/LICENSE.txt
AdresseParser-1.0.9.dist-info/METADATA
AdresseParser-1.0.9.dist-info/WHEEL
AdresseParser-1.0.9.dist-info/top_level.txt
AdresseParser-1.0.9.dist-info/RECORD
