Metadata-Version: 2.1
Name: AdresseParser
Version: 1.0.9
Summary: Parser d'adresses françaises
Home-page: UNKNOWN
Author: Maxime Challon
Author-email: maxime.challon@gmail.com
License: UNKNOWN
Keywords: adresse France
Platform: UNKNOWN
Classifier: Intended Audience :: Developers
Classifier: License :: OSI Approved :: MIT License
Classifier: Natural Language :: French
Classifier: Programming Language :: Python :: 3.7
Classifier: Topic :: Education
Requires-Dist: pandas (>=0.24.2)
